napari_workflows/__init__.py
napari_workflows/_io_yaml_v1.py
napari_workflows/_undo_redo_functionality.py
napari_workflows/_workflow.py
napari_workflows/_tests/__init__.py
napari_workflows/_tests/test_function.py
napari_workflows-0.2.11.dist-info/LICENSE
napari_workflows-0.2.11.dist-info/METADATA
napari_workflows-0.2.11.dist-info/WHEEL
napari_workflows-0.2.11.dist-info/top_level.txt
napari_workflows-0.2.11.dist-info/RECORD
