Metadata-Version: 2.1
Name: napari-workflows
Version: 0.2.11
Summary: Data structures for managing image processing workflows in napari
Home-page: https://github.com/haesleinhuepf/napari-workflows
Author: Robert Haase, Ryan Savill
Author-email: robert.haase@tu-dresden.de
License: BSD-3-Clause
Project-URL: Bug Tracker, https://github.com/haesleinhuepf/napari-workflows/issues
Project-URL: Documentation, https://github.com/haesleinhuepf/napari-workflows#README.md
Project-URL: Source Code, https://github.com/haesleinhuepf/napari-workflows
Project-URL: User Support, https://github.com/haesleinhuepf/napari-workflows/issues
Classifier: Development Status :: 3 - Alpha
Classifier: Intended Audience :: Developers
Classifier: Topic :: Scientific/Engineering :: Image Processing
Classifier: Programming Language :: Python
Classifier: Programming Language :: Python :: 3
Classifier: Programming Language :: Python :: 3.7
Classifier: Programming Language :: Python :: 3.8
Classifier: Programming Language :: Python :: 3.9
Classifier: Operating System :: OS Independent
Classifier: License :: OSI Approved :: BSD License
Requires-Python: >=3.7
License-File: LICENSE
Requires-Dist: numpy
Requires-Dist: napari
Requires-Dist: dask
Requires-Dist: autopep8
Requires-Dist: stackview
